{
  "version": "5",
  "dialect": "pg",
  "entries": [
    {
      "idx": 0,
      "version": "5",
      "when": 1707141540696,
      "tag": "0000_heavy_hydra",
      "breakpoints": true
    },
    {
      "idx": 1,
      "version": "5",
      "when": 1707142502665,
      "tag": "0001_flashy_bill_hollister",
      "breakpoints": true
    },
    {
      "idx": 2,
      "version": "5",
      "when": 1707144537098,
      "tag": "0002_cuddly_iron_monger",
      "breakpoints": true
    },
    {
      "idx": 3,
      "version": "5",
      "when": 1707145840801,
      "tag": "0003_jittery_blink",
      "breakpoints": true
    },
    {
      "idx": 4,
      "version": "5",
      "when": 1707161209989,
      "tag": "0004_steep_stephen_strange",
      "breakpoints": true
    }
  ]
}